aerocaps/__init__.py
aerocaps/version.py
aerocaps/examples/__init__.py
aerocaps/examples/bezier_surface.py
aerocaps/examples/fill_surface.py
aerocaps/examples/iges_export.py
aerocaps/examples/rational_bezier_curve.py
aerocaps/geom/__init__.py
aerocaps/geom/curves.py
aerocaps/geom/geometry_container.py
aerocaps/geom/intersection.py
aerocaps/geom/nurbs_purepython.py
aerocaps/geom/plane.py
aerocaps/geom/point.py
aerocaps/geom/surfaces.py
aerocaps/geom/tools.py
aerocaps/geom/transformation.py
aerocaps/geom/vector.py
aerocaps/iges/__init__.py
aerocaps/iges/curves.py
aerocaps/iges/entity.py
aerocaps/iges/examples.py
aerocaps/iges/global_params.py
aerocaps/iges/iges_generator.py
aerocaps/iges/iges_param.py
aerocaps/iges/point.py
aerocaps/iges/start_end_section.py
aerocaps/iges/surfaces.py
aerocaps/iges/transformation.py
aerocaps/scripts/__init__.py
aerocaps/scripts/make_curve_plots.py
aerocaps/scripts/make_surface_plots.py
aerocaps/scripts/rust_speed_test.py
aerocaps/stl/__init__.py
aerocaps/stl/stl_generator.py
aerocaps/tests/__init__.py
aerocaps/tests/test_fill_surface.py
aerocaps/tests/test_surface_continuity_optimizer.py
aerocaps/tests/test_surfaces.py
aerocaps/units/__init__.py
aerocaps/units/angle.py
aerocaps/units/area.py
aerocaps/units/length.py
aerocaps/units/unit.py
aerocaps/utils/__init__.py
aerocaps/utils/array.py
aerocaps/utils/iteration.py
aerocaps/utils/math.py
aerocaps/utils/plotting.py
aerocaps-0.3.2.dist-info/licenses/LICENSE
aerocaps-0.3.2.dist-info/METADATA
aerocaps-0.3.2.dist-info/WHEEL
aerocaps-0.3.2.dist-info/top_level.txt
aerocaps-0.3.2.dist-info/RECORD
